bspred/Arrivals_model.h5
bspred/Departures_model.h5
bspred/__init__.py
bspred/bs_matrix.py
bspred/get_path.py
bspred/nbhd_p.py
bspred/output_scale.csv
bspred/pre_by_model.py
bspred/scale.csv
bspred/stations_reshaped.csv
bspred/city_data/Bus.csv
bspred/city_data/Business.csv
bspred/city_data/Felony.csv
bspred/city_data/MTA.csv
bspred/city_data/Misdemeanor.csv
bspred/city_data/Property.csv
bspred/city_data/Violation.csv
bspred-0.0.5.dist-info/LICENSE
bspred-0.0.5.dist-info/METADATA
bspred-0.0.5.dist-info/WHEEL
bspred-0.0.5.dist-info/top_level.txt
bspred-0.0.5.dist-info/RECORD
