Metadata-Version: 2.1
Name: bspred
Version: 0.0.5
Summary: Prediction of bike sharing usage.
Home-page: https://github.com/jasonyiww/bspred
Author: Yiwen Wang
Author-email: yiwenwang9702@gmail.com
License: UNKNOWN
Platform: UNKNOWN
Classifier: Programming Language :: Python :: 3
Classifier: License :: OSI Approved :: MIT License
Classifier: Operating System :: OS Independent
Requires-Dist: keras
